nonebot_plugin_fishspeech_tts-0.3.9.dist-info/METADATA
nonebot_plugin_fishspeech_tts-0.3.9.dist-info/WHEEL
nonebot_plugin_fishspeech_tts-0.3.9.dist-info/entry_points.txt
nonebot_plugin_fishspeech_tts-0.3.9.dist-info/licenses/LICENSE
nonebot_plugin_fishspeech_tts/__init__.py
nonebot_plugin_fishspeech_tts/config.py
nonebot_plugin_fishspeech_tts/exception.py
nonebot_plugin_fishspeech_tts/files.py
nonebot_plugin_fishspeech_tts/fish_audio_api.py
nonebot_plugin_fishspeech_tts/fish_speech_api.py
nonebot_plugin_fishspeech_tts/matcher.py
nonebot_plugin_fishspeech_tts/on_start_up.py
nonebot_plugin_fishspeech_tts/request_params.py
nonebot_plugin_fishspeech_tts-0.3.9.dist-info/RECORD
