Metadata-Version: 2.1
Name: nonebot-plugin-fishspeech-tts
Version: 0.3.9
Summary: 小样本TTS,通过调用在线或本地api发送TTS语音
Author-Email: Cvandia <106718176+Cvandia@users.noreply.github.com>
License: MIT
Requires-Python: <4.0,>=3.10
Requires-Dist: ormsgpack<2.0.0,>=1.7.0
Requires-Dist: httpx>=0.27.0
Requires-Dist: nonebot2>=2.2.0
Requires-Dist: nonebot-plugin-alconna>=0.46.4
